datum/__init__.py
datum/analyzer.py
datum/base.py
datum/component.py
datum/const.py
datum/dice.lark
datum/error.py
datum/parser.py
datum/result.py
datum/util.py
epicteller_datum-0.4.1.dist-info/AUTHORS.rst
epicteller_datum-0.4.1.dist-info/LICENSE
epicteller_datum-0.4.1.dist-info/METADATA
epicteller_datum-0.4.1.dist-info/WHEEL
epicteller_datum-0.4.1.dist-info/top_level.txt
epicteller_datum-0.4.1.dist-info/RECORD
