Metadata-Version: 2.1
Name: epicteller-datum
Version: 0.4.1
Summary: Dice parser for Epicteller.
Home-page: https://github.com/epicteller/datum
Author: Kawashiro Nitori
Author-email: nitori@ikazuchi.cn
License: GNU General Public License v3
Keywords: datum
Platform: UNKNOWN
Classifier: Intended Audience :: Developers
Classifier: License :: OSI Approved :: GNU General Public License v3 (GPLv3)
Classifier: Natural Language :: Chinese (Simplified)
Classifier: Programming Language :: Python :: 3
Classifier: Programming Language :: Python :: 3.4
Classifier: Programming Language :: Python :: 3.5
Classifier: Programming Language :: Python :: 3.6
Classifier: Programming Language :: Python :: 3.7
Requires-Dist: lark-parser (>=0.7.1)
